napm/__init__.py
napm/config.py
napm/pseudo_install.py
napm/remove.py
napm/update.py
napm/utils.py
napm/warmup.py
napm-1.0.1.dist-info/LICENSE
napm-1.0.1.dist-info/WHEEL
napm-1.0.1.dist-info/METADATA
napm-1.0.1.dist-info/RECORD
