Metadata-Version: 2.1
Name: napm
Version: 1.0.1
Summary: Not A Package Manager.
License: MIT
Author: David Marx
Author-email: david.marx84@gmail.com
Requires-Python: >=3.7
Classifier: License :: OSI Approved :: MIT License
Classifier: Programming Language :: Python :: 3
Classifier: Programming Language :: Python :: 3.10
Classifier: Programming Language :: Python :: 3.7
Classifier: Programming Language :: Python :: 3.8
Classifier: Programming Language :: Python :: 3.9
Requires-Dist: gdown (>=4.4.0,<5.0.0)
Requires-Dist: loguru (>=0.6.0,<0.7.0)
Requires-Dist: omegaconf (>=2.1.1,<3.0.0)
Requires-Dist: requests (>=2.27.1,<3.0.0)
